openxc/__init__.py
openxc/interface.py
openxc/logconfig.py
openxc/measurements.py
openxc/openxc_pb2.py
openxc/units.py
openxc/utils.py
openxc/vehicle.py
openxc/version.py
openxc/controllers/__init__.py
openxc/controllers/base.py
openxc/controllers/serial.py
openxc/controllers/usb.py
openxc/formats/__init__.py
openxc/formats/base.py
openxc/formats/binary.py
openxc/formats/json.py
openxc/generator/__init__.py
openxc/generator/coder.py
openxc/generator/message_sets.py
openxc/generator/signals.cpp.footer
openxc/generator/signals.cpp.header
openxc/generator/structures.py
openxc/generator/xml_to_json.py
openxc/sinks/__init__.py
openxc/sinks/base.py
openxc/sinks/notifier.py
openxc/sinks/queued.py
openxc/sinks/recorder.py
openxc/sinks/uploader.py
openxc/sources/__init__.py
openxc/sources/base.py
openxc/sources/bluetooth.py
openxc/sources/network.py
openxc/sources/serial.py
openxc/sources/socket.py
openxc/sources/trace.py
openxc/sources/usb.py
openxc/tools/__init__.py
openxc/tools/args.py
openxc/tools/common.py
openxc/tools/control.py
openxc/tools/dashboard.py
openxc/tools/diagnostics.py
openxc/tools/dump.py
openxc/tools/generate_code.py
openxc/tools/gps.py
openxc/tools/obd2scanner.py
openxc/tools/scanner.py
openxc/tools/tracesplit.py
openxc/tools/static/css/dashboard.css
openxc/tools/static/js/dashboard.js
openxc/tools/static/js/jquery-3.4.1.min.js
openxc/tools/static/js/jquery.color-2.1.2.min.js
openxc/tools/static/js/socket.io.slim.js
openxc/tools/templates/dashboard.html
openxc-2.2.0.dist-info/AUTHORS
openxc-2.2.0.dist-info/LICENSE
openxc-2.2.0.dist-info/METADATA
openxc-2.2.0.dist-info/WHEEL
openxc-2.2.0.dist-info/entry_points.txt
openxc-2.2.0.dist-info/top_level.txt
openxc-2.2.0.dist-info/RECORD
