Metadata-Version: 2.1
Name: openxc
Version: 2.2.0
Summary: A Python library to connect to an OpenXC vehicle interface
Home-page: http://github.com/openxc/openxc-python
Author: Christopher Peplin
Author-email: cpeplin@ford.com
License: BSD
Platform: UNKNOWN
Classifier: Development Status :: 4 - Beta
Classifier: License :: OSI Approved :: BSD License
Classifier: Operating System :: OS Independent
Classifier: Programming Language :: Python
Classifier: Topic :: Software Development
Requires-Dist: pyusb (==1.0.0a3)
Requires-Dist: units (>=0.5)
Requires-Dist: argparse
Requires-Dist: requests (==2.20.0)
Requires-Dist: protobuf (==3.17.1)
Provides-Extra: bluetooth
Requires-Dist: pybluez ; extra == 'bluetooth'
Provides-Extra: lxml
Requires-Dist: lxml ; extra == 'lxml'
Provides-Extra: serial
Requires-Dist: pyserial (==3.1.1) ; extra == 'serial'
